pysumstats/__init__.py
pysumstats/base.py
pysumstats/exceptions.py
pysumstats/sumstats.py
pysumstats/utils.py
pysumstats/plot/__init__.py
pysumstats/plot/manhattan.py
pysumstats/plot/qcplots.py
pysumstats/plot/qq.py
pysumstats-0.5.2.dist-info/LICENSE
pysumstats-0.5.2.dist-info/METADATA
pysumstats-0.5.2.dist-info/WHEEL
pysumstats-0.5.2.dist-info/top_level.txt
pysumstats-0.5.2.dist-info/RECORD
